Workbook

Sheet Instrucciones
A1: Matriz IGO – Análisis prospectivo de Imaginamos S.A.S. (horizonte 2036)
A3: Cómo usar este libro
A4: 1. En la hoja Matriz_30, edite solo las celdas en azul con fondo amarillo: P, M, F y G (escala 1 a 5).
A5: 2. La importancia se calcula como el promedio de P, M y F, redondeado a un decimal.
A6: 3. El cuadrante IGO se asigna automáticamente: Reto inmediato (Imp ≥ umbral y G ≥ umbral), Reto mediato (Imp ≥ umbral y G < umbral), Menos urgente, Innecesario.
A7: 4. Los umbrales se pueden ajustar en esta hoja (celdas B12 y B13).
A8: 5. Las hojas Resumen y Ranking_Top10 y el gráfico se actualizan solos.
A10: Criterios: P = probabilidad de ocurrencia; M = magnitud del impacto estratégico; F = impacto financiero; G = gobernabilidad (control de la empresa).
A12: Umbral de importancia alta | B12: 3.5 | C12: Supuesto del autor (Godet, 2007: punto medio de la escala)
A13: Umbral de gobernabilidad alta | B13: 3

Sheet Matriz_30
A1: Cód. | B1: Variable | C1: Descripción y evidencia | D1: Tipo | E1: Dimensión | F1: Dirección | G1: Horizonte | H1: Fuente | I1: P | J1: M | K1: F | L1: Importancia | M1: G | N1: Impacto financiero | O1: Cuadrante IGO | P1: Clave orden
A2: V01 | B2: Política nacional de inteligencia artificial | C2: El CONPES 4144 (feb. 2025) fija una hoja de ruta de IA a 2030 con presupuesto público estimado en COP 479.000 millones; impulsa la demanda de proyectos de adopción de IA en empresas y entidades. | D2: Externa | E2: Político | F2: Creciente | G2: Mediano | H2: DNP (2025) | I2: 5 | J2: 4 | K2: 3 | L2: =ROUND(AVERAGE(I2:K2),1) -> 4 | M2: 2 | N2: Ingresos | O2: =IF(L2>=Instrucciones!$B$12,IF(M2>=Instrucciones!$B$13,"Reto inmediato","Reto mediato"),IF(M2>=Instrucciones!$B$13,"Menos urgente","Innecesario")) -> Reto mediato | P2: =L2+M2/100+(100-ROW())/100000 -> 4.02098
A3: V02 | B3: Transición de gobierno 2026 | C3: El cambio de gobierno de agosto de 2026 puede modificar prioridades, incentivos y continuidad de los programas públicos de transformación digital. | D3: Externa | E3: Político | F3: Incierta | G3: Corto | H3: Autor | I3: 5 | J3: 2 | K3: 2 | L3: =ROUND(AVERAGE(I3:K3),1) -> 3 | M3: 1 | N3: Riesgo | O3: =IF(L3>=Instrucciones!$B$12,IF(M3>=Instrucciones!$B$13,"Reto inmediato","Reto mediato"),IF(M3>=Instrucciones!$B$13,"Menos urgente","Innecesario")) -> Innecesario | P3: =L3+M3/100+(100-ROW())/100000 -> 3.01097
A4: V03 | B4: Transformación digital del Estado | C4: La digitalización de trámites y servicios públicos amplía un mercado ya atendido por la empresa (p. ej., ETB), con procesos de contratación exigentes y ciclos de pago largos. | D4: Externa | E4: Político | F4: Creciente | G4: Mediano | H4: DNP (2025); Imaginamos (s. f.-a) | I4: 4 | J4: 3 | K4: 3 | L4: =ROUND(AVERAGE(I4:K4),1) -> 3.3 | M4: 2 | N4: Ingresos | O4: =IF(L4>=Instrucciones!$B$12,IF(M4>=Instrucciones!$B$13,"Reto inmediato","Reto mediato"),IF(M4>=Instrucciones!$B$13,"Menos urgente","Innecesario")) -> Innecesario | P4: =L4+M4/100+(100-ROW())/100000 -> 3.32096
A5: V04 | B5: Volatilidad de la tasa de cambio COP/USD | C5: Un peso débil mejora la competitividad de la exportación de servicios; uno fuerte la reduce y encarece licencias y nube facturadas en dólares. | D5: Externa | E5: Económico | F5: Incierta | G5: Corto | H5: Autor | I5: 5 | J5: 4 | K5: 4 | L5: =ROUND(AVERAGE(I5:K5),1) -> 4.3 | M5: 1 | N5: Ingresos y costos | O5: =IF(L5>=Instrucciones!$B$12,IF(M5>=Instrucciones!$B$13,"Reto inmediato","Reto mediato"),IF(M5>=Instrucciones!$B$13,"Menos urgente","Innecesario")) -> Reto mediato | P5: =L5+M5/100+(100-ROW())/100000 -> 4.31095
A6: V05 | B6: Desaceleración del sector y presupuestos TI | C6: El sector creció 0,8 % en 2024 y se recuperó gradualmente en 2025; los clientes recortan o aplazan proyectos a la medida. | D6: Externa | E6: Económico | F6: Cíclica | G6: Corto | H6: Fedesoft (2025) | I6: 4 | J6: 4 | K6: 5 | L6: =ROUND(AVERAGE(I6:K6),1) -> 4.3 | M6: 1 | N6: Ingresos | O6: =IF(L6>=Instrucciones!$B$12,IF(M6>=Instrucciones!$B$13,"Reto inmediato","Reto mediato"),IF(M6>=Instrucciones!$B$13,"Menos urgente","Innecesario")) -> Reto mediato | P6: =L6+M6/100+(100-ROW())/100000 -> 4.31094
A7: V06 | B7: Nearshoring de servicios de software | C7: Empresas de EE. UU. trasladan desarrollo a países con huso horario cercano; las exportaciones de servicios informáticos superaron USD 1.758 millones en 2024. | D7: Externa | E7: Económico | F7: Creciente | G7: Mediano | H7: Fedesoft (2025) | I7: 4 | J7: 5 | K7: 5 | L7: =ROUND(AVERAGE(I7:K7),1) -> 4.7 | M7: 2 | N7: Ingresos | O7: =IF(L7>=Instrucciones!$B$12,IF(M7>=Instrucciones!$B$13,"Reto inmediato","Reto mediato"),IF(M7>=Instrucciones!$B$13,"Menos urgente","Innecesario")) -> Reto mediato | P7: =L7+M7/100+(100-ROW())/100000 -> 4.72093
A8: V07 | B8: Costo del financiamiento para pymes | C8: Las tasas de interés y el acceso limitado a crédito condicionan la inversión en productos propios, I+D y expansión comercial. | D8: Externa | E8: Económico | F8: Estable | G8: Corto | H8: Autor | I8: 4 | J8: 3 | K8: 3 | L8: =ROUND(AVERAGE(I8:K8),1) -> 3.3 | M8: 1 | N8: Inversión | O8: =IF(L8>=Instrucciones!$B$12,IF(M8>=Instrucciones!$B$13,"Reto inmediato","Reto mediato"),IF(M8>=Instrucciones!$B$13,"Menos urgente","Innecesario")) -> Innecesario | P8: =L8+M8/100+(100-ROW())/100000 -> 3.31092
A9: V08 | B9: Brecha de talento TI | C9: Déficit estimado de 83.000 profesionales que podría llegar a 89.000 en 2030; presiona salarios y disponibilidad de perfiles especializados. | D9: Externa | E9: Social | F9: Creciente | G9: Largo | H9: Forbes Colombia (2026) | I9: 5 | J9: 5 | K9: 4 | L9: =ROUND(AVERAGE(I9:K9),1) -> 4.7 | M9: 2 | N9: Costos | O9: =IF(L9>=Instrucciones!$B$12,IF(M9>=Instrucciones!$B$13,"Reto inmediato","Reto mediato"),IF(M9>=Instrucciones!$B$13,"Menos urgente","Innecesario")) -> Reto mediato | P9: =L9+M9/100+(100-ROW())/100000 -> 4.72091
A10: V09 | B10: Trabajo remoto y competencia global por talento | C10: Los profesionales colombianos pueden trabajar para empresas extranjeras con salarios en dólares, lo que eleva la rotación y el costo de retención. | D10: Externa | E10: Social | F10: Creciente | G10: Mediano | H10: Autor | I10: 5 | J10: 4 | K10: 4 | L10: =ROUND(AVERAGE(I10:K10),1) -> 4.3 | M10: 2 | N10: Costos | O10: =IF(L10>=Instrucciones!$B$12,IF(M10>=Instrucciones!$B$13,"Reto inmediato","Reto mediato"),IF(M10>=Instrucciones!$B$13,"Menos urgente","Innecesario")) -> Reto mediato | P10: =L10+M10/100+(100-ROW())/100000 -> 4.3209
A11: V10 | B11: Digitalización de pymes y consumidores | C11: Más empresas y usuarios exigen canales digitales, comercio electrónico y apps, lo que amplía el mercado potencial de servicios digitales. | D11: Externa | E11: Social | F11: Creciente | G11: Mediano | H11: La República (2025) | I11: 5 | J11: 4 | K11: 4 | L11: =ROUND(AVERAGE(I11:K11),1) -> 4.3 | M11: 2 | N11: Ingresos | O11: =IF(L11>=Instrucciones!$B$12,IF(M11>=Instrucciones!$B$13,"Reto inmediato","Reto mediato"),IF(M11>=Instrucciones!$B$13,"Menos urgente","Innecesario")) -> Reto mediato | P11: =L11+M11/100+(100-ROW())/100000 -> 4.32089
A12: V11 | B12: Mayores expectativas de experiencia de usuario | C12: Las nuevas generaciones esperan productos digitales intuitivos, personalizados e inmediatos; el diseño UX/UI se vuelve un diferenciador. | D12: Externa | E12: Social | F12: Creciente | G12: Largo | H12: Autor | I12: 5 | J12: 3 | K12: 2 | L12: =ROUND(AVERAGE(I12:K12),1) -> 3.3 | M12: 3 | N12: Ingresos | O12: =IF(L12>=Instrucciones!$B$12,IF(M12>=Instrucciones!$B$13,"Reto inmediato","Reto mediato"),IF(M12>=Instrucciones!$B$13,"Menos urgente","Innecesario")) -> Menos urgente | P12: =L12+M12/100+(100-ROW())/100000 -> 3.33088
A13: V12 | B13: IA generativa y agentes en el desarrollo de software | C13: Asistentes de código y agentes de IA reducen tiempos y costos de desarrollo; cambian el modelo de cobro por horas y la composición de los equipos. El 68 % de las empresas de software prioriza la IA. | D13: Externa | E13: Tecnológico | F13: Disruptiva | G13: Corto | H13: La República (2025) | I13: 5 | J13: 5 | K13: 5 | L13: =ROUND(AVERAGE(I13:K13),1) -> 5 | M13: 3 | N13: Ingresos y costos | O13: =IF(L13>=Instrucciones!$B$12,IF(M13>=Instrucciones!$B$13,"Reto inmediato","Reto mediato"),IF(M13>=Instrucciones!$B$13,"Menos urgente","Innecesario")) -> Reto inmediato | P13: =L13+M13/100+(100-ROW())/100000 -> 5.03087
... A31: V30 | B31: Presencia comercial internacional limitada | C31: Operación concentrada en Colombia y Latinoamérica, con menor fuerza comercial que los competidores multinacionales en EE. UU. | D31: Interna | E31: Debilidad | F31: Estable | G31: Mediano | H31: Autor | I31: 4 | J31: 4 | K31: 5 | L31: =ROUND(AVERAGE(I31:K31),1) -> 4.3 | M31: 3 | N31: Ingresos | O31: =IF(L31>=Instrucciones!$B$12,IF(M31>=Instrucciones!$B$13,"Reto inmediato","Reto mediato"),IF(M31>=Instrucciones!$B$13,"Menos urgente","Innecesario")) -> Reto inmediato | P31: =L31+M31/100+(100-ROW())/100000 -> 4.33069

Sheet Resumen
A1: Dimensión | B1: N.º variables | C1: Importancia promedio | D1: Gobernabilidad promedio
A2: Político | B2: =COUNTIF(Matriz_30!$E$2:$E$31,A2) -> 3 | C2: =IFERROR(AVERAGEIF(Matriz_30!$E$2:$E$31,A2,Matriz_30!$L$2:$L$31),0) -> 3.4333333 | D2: =IFERROR(AVERAGEIF(Matriz_30!$E$2:$E$31,A2,Matriz_30!$M$2:$M$31),0) -> 1.6666667
A3: Económico | B3: =COUNTIF(Matriz_30!$E$2:$E$31,A3) -> 4 | C3: =IFERROR(AVERAGEIF(Matriz_30!$E$2:$E$31,A3,Matriz_30!$L$2:$L$31),0) -> 4.15 | D3: =IFERROR(AVERAGEIF(Matriz_30!$E$2:$E$31,A3,Matriz_30!$M$2:$M$31),0) -> 1.25
A4: Social | B4: =COUNTIF(Matriz_30!$E$2:$E$31,A4) -> 4 | C4: =IFERROR(AVERAGEIF(Matriz_30!$E$2:$E$31,A4,Matriz_30!$L$2:$L$31),0) -> 4.15 | D4: =IFERROR(AVERAGEIF(Matriz_30!$E$2:$E$31,A4,Matriz_30!$M$2:$M$31),0) -> 2.25
A5: Tecnológico | B5: =COUNTIF(Matriz_30!$E$2:$E$31,A5) -> 4 | C5: =IFERROR(AVERAGEIF(Matriz_30!$E$2:$E$31,A5,Matriz_30!$L$2:$L$31),0) -> 4.15 | D5: =IFERROR(AVERAGEIF(Matriz_30!$E$2:$E$31,A5,Matriz_30!$M$2:$M$31),0) -> 2.75
A6: Ecológico | B6: =COUNTIF(Matriz_30!$E$2:$E$31,A6) -> 2 | C6: =IFERROR(AVERAGEIF(Matriz_30!$E$2:$E$31,A6,Matriz_30!$L$2:$L$31),0) -> 2 | D6: =IFERROR(AVERAGEIF(Matriz_30!$E$2:$E$31,A6,Matriz_30!$M$2:$M$31),0) -> 3.5
A7: Legal | B7: =COUNTIF(Matriz_30!$E$2:$E$31,A7) -> 3 | C7: =IFERROR(AVERAGEIF(Matriz_30!$E$2:$E$31,A7,Matriz_30!$L$2:$L$31),0) -> 3.6666667 | D7: =IFERROR(AVERAGEIF(Matriz_30!$E$2:$E$31,A7,Matriz_30!$M$2:$M$31),0) -> 1.6666667
A8: Fortaleza | B8: =COUNTIF(Matriz_30!$E$2:$E$31,A8) -> 5 | C8: =IFERROR(AVERAGEIF(Matriz_30!$E$2:$E$31,A8,Matriz_30!$L$2:$L$31),0) -> 3.72 | D8: =IFERROR(AVERAGEIF(Matriz_30!$E$2:$E$31,A8,Matriz_30!$M$2:$M$31),0) -> 4.2
A9: Debilidad | B9: =COUNTIF(Matriz_30!$E$2:$E$31,A9) -> 5 | C9: =IFERROR(AVERAGEIF(Matriz_30!$E$2:$E$31,A9,Matriz_30!$L$2:$L$31),0) -> 4.06 | D9: =IFERROR(AVERAGEIF(Matriz_30!$E$2:$E$31,A9,Matriz_30!$M$2:$M$31),0) -> 3.2
A10: Total | B10: =SUM(B2:B9) -> 30 | C10: =AVERAGE(Matriz_30!L2:L31) -> 3.8 | D10: =AVERAGE(Matriz_30!M2:M31) -> 2.6333333
A12: Cuadrante IGO | B12: N.º variables | C12: % del total
A13: Reto inmediato | B13: =COUNTIF(Matriz_30!$O$2:$O$31,A13) -> 8 | C13: =B13/30 -> 0.26666667
A14: Reto mediato | B14: =COUNTIF(Matriz_30!$O$2:$O$31,A14) -> 11 | C14: =B14/30 -> 0.36666667
A15: Menos urgente | B15: =COUNTIF(Matriz_30!$O$2:$O$31,A15) -> 7 | C15: =B15/30 -> 0.23333333
A16: Innecesario | B16: =COUNTIF(Matriz_30!$O$2:$O$31,A16) -> 4 | C16: =B16/30 -> 0.13333333

Sheet Ranking_Top10
A1: Ranking preliminar por importancia (desempate por gobernabilidad). El ranking definitivo de las 10 variables clave se construye en la entrega 2.
A3: Puesto | B3: Cód. | C3: Variable | D3: Dimensión | E3: Importancia | F3: G | G3: Cuadrante IGO
A4: 1 | B4: =INDEX(Matriz_30!$A$2:$A$31,MATCH(LARGE(Matriz_30!$P$2:$P$31,A4),Matriz_30!$P$2:$P$31,0)) -> V29 | C4: =INDEX(Matriz_30!$B$2:$B$31,MATCH(LARGE(Matriz_30!$P$2:$P$31,A4),Matriz_30!$P$2:$P$31,0)) -> Ingresos concentrados en proyectos a la medida | D4: =INDEX(Matriz_30!$E$2:$E$31,MATCH(LARGE(Matriz_30!$P$2:$P$31,A4),Matriz_30!$P$2:$P$31,0)) -> Debilidad | E4: =INDEX(Matriz_30!$L$2:$L$31,MATCH(LARGE(Matriz_30!$P$2:$P$31,A4),Matriz_30!$P$2:$P$31,0)) -> 5 | F4: =INDEX(Matriz_30!$M$2:$M$31,MATCH(LARGE(Matriz_30!$P$2:$P$31,A4),Matriz_30!$P$2:$P$31,0)) -> 4 | G4: =INDEX(Matriz_30!$O$2:$O$31,MATCH(LARGE(Matriz_30!$P$2:$P$31,A4),Matriz_30!$P$2:$P$31,0)) -> Reto inmediato
A5: 2 | B5: =INDEX(Matriz_30!$A$2:$A$31,MATCH(LARGE(Matriz_30!$P$2:$P$31,A5),Matriz_30!$P$2:$P$31,0)) -> V12 | C5: =INDEX(Matriz_30!$B$2:$B$31,MATCH(LARGE(Matriz_30!$P$2:$P$31,A5),Matriz_30!$P$2:$P$31,0)) -> IA generativa y agentes en el desarrollo de software | D5: =INDEX(Matriz_30!$E$2:$E$31,MATCH(LARGE(Matriz_30!$P$2:$P$31,A5),Matriz_30!$P$2:$P$31,0)) -> Tecnológico | E5: =INDEX(Matriz_30!$L$2:$L$31,MATCH(LARGE(Matriz_30!$P$2:$P$31,A5),Matriz_30!$P$2:$P$31,0)) -> 5 | F5: =INDEX(Matriz_30!$M$2:$M$31,MATCH(LARGE(Matriz_30!$P$2:$P$31,A5),Matriz_30!$P$2:$P$31,0)) -> 3 | G5: =INDEX(Matriz_30!$O$2:$O$31,MATCH(LARGE(Matriz_30!$P$2:$P$31,A5),Matriz_30!$P$2:$P$31,0)) -> Reto inmediato
A6: 3 | B6: =INDEX(Matriz_30!$A$2:$A$31,MATCH(LARGE(Matriz_30!$P$2:$P$31,A6),Matriz_30!$P$2:$P$31,0)) -> V06 | C6: =INDEX(Matriz_30!$B$2:$B$31,MATCH(LARGE(Matriz_30!$P$2:$P$31,A6),Matriz_30!$P$2:$P$31,0)) -> Nearshoring de servicios de software | D6: =INDEX(Matriz_30!$E$2:$E$31,MATCH(LARGE(Matriz_30!$P$2:$P$31,A6),Matriz_30!$P$2:$P$31,0)) -> Económico | E6: =INDEX(Matriz_30!$L$2:$L$31,MATCH(LARGE(Matriz_30!$P$2:$P$31,A6),Matriz_30!$P$2:$P$31,0)) -> 4.7 | F6: =INDEX(Matriz_30!$M$2:$M$31,MATCH(LARGE(Matriz_30!$P$2:$P$31,A6),Matriz_30!$P$2:$P$31,0)) -> 2 | G6: =INDEX(Matriz_30!$O$2:$O$31,MATCH(LARGE(Matriz_30!$P$2:$P$31,A6),Matriz_30!$P$2:$P$31,0)) -> Reto mediato
A7: 4 | B7: =INDEX(Matriz_30!$A$2:$A$31,MATCH(LARGE(Matriz_30!$P$2:$P$31,A7),Matriz_30!$P$2:$P$31,0)) -> V08 | C7: =INDEX(Matriz_30!$B$2:$B$31,MATCH(LARGE(Matriz_30!$P$2:$P$31,A7),Matriz_30!$P$2:$P$31,0)) -> Brecha de talento TI | D7: =INDEX(Matriz_30!$E$2:$E$31,MATCH(LARGE(Matriz_30!$P$2:$P$31,A7),Matriz_30!$P$2:$P$31,0)) -> Social | E7: =INDEX(Matriz_30!$L$2:$L$31,MATCH(LARGE(Matriz_30!$P$2:$P$31,A7),Matriz_30!$P$2:$P$31,0)) -> 4.7 | F7: =INDEX(Matriz_30!$M$2:$M$31,MATCH(LARGE(Matriz_30!$P$2:$P$31,A7),Matriz_30!$P$2:$P$31,0)) -> 2 | G7: =INDEX(Matriz_30!$O$2:$O$31,MATCH(LARGE(Matriz_30!$P$2:$P$31,A7),Matriz_30!$P$2:$P$31,0)) -> Reto mediato
A8: 5 | B8: =INDEX(Matriz_30!$A$2:$A$31,MATCH(LARGE(Matriz_30!$P$2:$P$31,A8),Matriz_30!$P$2:$P$31,0)) -> V15 | C8: =INDEX(Matriz_30!$B$2:$B$31,MATCH(LARGE(Matriz_30!$P$2:$P$31,A8),Matriz_30!$P$2:$P$31,0)) -> Ciberseguridad y desarrollo seguro | D8: =INDEX(Matriz_30!$E$2:$E$31,MATCH(LARGE(Matriz_30!$P$2:$P$31,A8),Matriz_30!$P$2:$P$31,0)) -> Tecnológico | E8: =INDEX(Matriz_30!$L$2:$L$31,MATCH(LARGE(Matriz_30!$P$2:$P$31,A8),Matriz_30!$P$2:$P$31,0)) -> 4.3 | F8: =INDEX(Matriz_30!$M$2:$M$31,MATCH(LARGE(Matriz_30!$P$2:$P$31,A8),Matriz_30!$P$2:$P$31,0)) -> 3 | G8: =INDEX(Matriz_30!$O$2:$O$31,MATCH(LARGE(Matriz_30!$P$2:$P$31,A8),Matriz_30!$P$2:$P$31,0)) -> Reto inmediato
A9: 6 | B9: =INDEX(Matriz_30!$A$2:$A$31,MATCH(LARGE(Matriz_30!$P$2:$P$31,A9),Matriz_30!$P$2:$P$31,0)) -> V24 | C9: =INDEX(Matriz_30!$B$2:$B$31,MATCH(LARGE(Matriz_30!$P$2:$P$31,A9),Matriz_30!$P$2:$P$31,0)) -> Cartera de clientes corporativos | D9: =INDEX(Matriz_30!$E$2:$E$31,MATCH(LARGE(Matriz_30!$P$2:$P$31,A9),Matriz_30!$P$2:$P$31,0)) -> Fortaleza | E9: =INDEX(Matriz_30!$L$2:$L$31,MATCH(LARGE(Matriz_30!$P$2:$P$31,A9),Matriz_30!$P$2:$P$31,0)) -> 4.3 | F9: =INDEX(Matriz_30!$M$2:$M$31,MATCH(LARGE(Matriz_30!$P$2:$P$31,A9),Matriz_30!$P$2:$P$31,0)) -> 3 | G9: =INDEX(Matriz_30!$O$2:$O$31,MATCH(LARGE(Matriz_30!$P$2:$P$31,A9),Matriz_30!$P$2:$P$31,0)) -> Reto inmediato
A10: 7 | B10: =INDEX(Matriz_30!$A$2:$A$31,MATCH(LARGE(Matriz_30!$P$2:$P$31,A10),Matriz_30!$P$2:$P$31,0)) -> V30 | C10: =INDEX(Matriz_30!$B$2:$B$31,MATCH(LARGE(Matriz_30!$P$2:$P$31,A10),Matriz_30!$P$2:$P$31,0)) -> Presencia comercial internacional limitada | D10: =INDEX(Matriz_30!$E$2:$E$31,MATCH(LARGE(Matriz_30!$P$2:$P$31,A10),Matriz_30!$P$2:$P$31,0)) -> Debilidad | E10: =INDEX(Matriz_30!$L$2:$L$31,MATCH(LARGE(Matriz_30!$P$2:$P$31,A10),Matriz_30!$P$2:$P$31,0)) -> 4.3 | F10: =INDEX(Matriz_30!$M$2:$M$31,MATCH(LARGE(Matriz_30!$P$2:$P$31,A10),Matriz_30!$P$2:$P$31,0)) -> 3 | G10: =INDEX(Matriz_30!$O$2:$O$31,MATCH(LARGE(Matriz_30!$P$2:$P$31,A10),Matriz_30!$P$2:$P$31,0)) -> Reto inmediato
A11: 8 | B11: =INDEX(Matriz_30!$A$2:$A$31,MATCH(LARGE(Matriz_30!$P$2:$P$31,A11),Matriz_30!$P$2:$P$31,0)) -> V09 | C11: =INDEX(Matriz_30!$B$2:$B$31,MATCH(LARGE(Matriz_30!$P$2:$P$31,A11),Matriz_30!$P$2:$P$31,0)) -> Trabajo remoto y competencia global por talento | D11: =INDEX(Matriz_30!$E$2:$E$31,MATCH(LARGE(Matriz_30!$P$2:$P$31,A11),Matriz_30!$P$2:$P$31,0)) -> Social | E11: =INDEX(Matriz_30!$L$2:$L$31,MATCH(LARGE(Matriz_30!$P$2:$P$31,A11),Matriz_30!$P$2:$P$31,0)) -> 4.3 | F11: =INDEX(Matriz_30!$M$2:$M$31,MATCH(LARGE(Matriz_30!$P$2:$P$31,A11),Matriz_30!$P$2:$P$31,0)) -> 2 | G11: =INDEX(Matriz_30!$O$2:$O$31,MATCH(LARGE(Matriz_30!$P$2:$P$31,A11),Matriz_30!$P$2:$P$31,0)) -> Reto mediato
A12: 9 | B12: =INDEX(Matriz_30!$A$2:$A$31,MATCH(LARGE(Matriz_30!$P$2:$P$31,A12),Matriz_30!$P$2:$P$31,0)) -> V10 | C12: =INDEX(Matriz_30!$B$2:$B$31,MATCH(LARGE(Matriz_30!$P$2:$P$31,A12),Matriz_30!$P$2:$P$31,0)) -> Digitalización de pymes y consumidores | D12: =INDEX(Matriz_30!$E$2:$E$31,MATCH(LARGE(Matriz_30!$P$2:$P$31,A12),Matriz_30!$P$2:$P$31,0)) -> Social | E12: =INDEX(Matriz_30!$L$2:$L$31,MATCH(LARGE(Matriz_30!$P$2:$P$31,A12),Matriz_30!$P$2:$P$31,0)) -> 4.3 | F12: =INDEX(Matriz_30!$M$2:$M$31,MATCH(LARGE(Matriz_30!$P$2:$P$31,A12),Matriz_30!$P$2:$P$31,0)) -> 2 | G12: =INDEX(Matriz_30!$O$2:$O$31,MATCH(LARGE(Matriz_30!$P$2:$P$31,A12),Matriz_30!$P$2:$P$31,0)) -> Reto mediato
A13: 10 | B13: =INDEX(Matriz_30!$A$2:$A$31,MATCH(LARGE(Matriz_30!$P$2:$P$31,A13),Matriz_30!$P$2:$P$31,0)) -> V26 | C13: =INDEX(Matriz_30!$B$2:$B$31,MATCH(LARGE(Matriz_30!$P$2:$P$31,A13),Matriz_30!$P$2:$P$31,0)) -> Escala reducida frente a grandes competidores | D13: =INDEX(Matriz_30!$E$2:$E$31,MATCH(LARGE(Matriz_30!$P$2:$P$31,A13),Matriz_30!$P$2:$P$31,0)) -> Debilidad | E13: =INDEX(Matriz_30!$L$2:$L$31,MATCH(LARGE(Matriz_30!$P$2:$P$31,A13),Matriz_30!$P$2:$P$31,0)) -> 4.3 | F13: =INDEX(Matriz_30!$M$2:$M$31,MATCH(LARGE(Matriz_30!$P$2:$P$31,A13),Matriz_30!$P$2:$P$31,0)) -> 2 | G13: =INDEX(Matriz_30!$O$2:$O$31,MATCH(LARGE(Matriz_30!$P$2:$P$31,A13),Matriz_30!$P$2:$P$31,0)) -> Reto mediato

Sheet Grafico_IGO
A1: Umbrales: importancia 3,5 y gobernabilidad 3. Ver figura 2 del documento para la versión etiquetada.
